AUTHORS.rst
CONTRIBUTING.rst
HISTORY.rst
LICENSE
MANIFEST.in
README.rst
setup.cfg
setup.py
admin_reorder/__init__.py
admin_reorder/middleware.py
admin_reorder/models.py
admin_reorder/static/css/admin-reorder.css
admin_reorder/static/js/admin-reorder.js
admin_reorder/templates/admin-reorder/base.html
django_modeladmin_reorder.egg-info/PKG-INFO
django_modeladmin_reorder.egg-info/SOURCES.txt
django_modeladmin_reorder.egg-info/dependency_links.txt
django_modeladmin_reorder.egg-info/not-zip-safe
django_modeladmin_reorder.egg-info/top_level.txt