Metadata-Version: 1.1
Name: django-modeladmin-reorder
Version: 0.1.1
Summary: Custom ordering for the apps and models in the admin app.
Home-page: https://github.com/mishbahr/django-modeladmin-reorder
Author: Mishbah Razzaque
Author-email: mishbahx@gmail.com
License: BSD
Keywords: django-modeladmin-reorder
Platform: UNKNOWN
Classifier: Development Status :: 2 - Pre-Alpha
Classifier: Framework :: Django
Classifier: Intended Audience :: Developers
Classifier: License :: OSI Approved :: BSD License
Classifier: Natural Language :: English
Classifier: Programming Language :: Python :: 2
Classifier: Programming Language :: Python :: 2.6
Classifier: Programming Language :: Python :: 2.7
Classifier: Programming Language :: Python :: 3
Classifier: Programming Language :: Python :: 3.3
